orchestra/__init__.py
orchestra/_version.py
orchestra/cli.py
orchestra/configuration.py
orchestra/lifecycle.py
orchestra/adapters/__init__.py
orchestra/adapters/base.py
orchestra/adapters/langchain.py
orchestra/adapters/langgraph.py
orchestra/agent/__init__.py
orchestra/agent/builder.py
orchestra/eval/__init__.py
orchestra/eval/asserts.py
orchestra/llm/__init__.py
orchestra/llm/factory.py
orchestra/mcp/__init__.py
orchestra/mcp/client.py
orchestra/mcp/registry.py
orchestra/mcp/tools.py
orchestra/monitoring/__init__.py
orchestra/monitoring/health.py
orchestra/monitoring/metrics.py
orchestra/recorder/__init__.py
orchestra/recorder/base.py
orchestra/recorder/event_listener.py
orchestra/recorder/logger.py
orchestra/recorder/storage.py
orchestra/resilience/__init__.py
orchestra/resilience/circuit_breaker.py
orchestra_llm_cache-0.3.0.dist-info/licenses/LICENSE
tests/__init__.py
tests/conftest.py
tests/test_eval.py
tests/test_recorder_production.py
tests/test_adapters/__init__.py
tests/test_adapters/test_langchain.py
tests/test_adapters/test_langgraph.py
tests/test_core/__init__.py
tests/test_core/test_cache_manager.py
tests/test_mcp/__init__.py
tests/test_mcp/test_registry.py
orchestra_llm_cache-0.3.0.dist-info/METADATA
orchestra_llm_cache-0.3.0.dist-info/WHEEL
orchestra_llm_cache-0.3.0.dist-info/top_level.txt
orchestra_llm_cache-0.3.0.dist-info/RECORD
