Metadata-Version: 2.4
Name: orchestra-llm-cache
Version: 0.3.0
Summary: Reduce AI orchestration costs by 85% with semantic caching
Home-page: https://github.com/uejsh/orchestra
Author: Orchestra Team
Author-email: Orchestra Team <team@orchestra.ai>
Classifier: Development Status :: 3 - Alpha
Classifier: Intended Audience :: Developers
Classifier: License :: OSI Approved :: MIT License
Classifier: Programming Language :: Python :: 3
Requires-Python: >=3.9
License-File: LICENSE
Requires-Dist: numpy>=1.24.0
Requires-Dist: sentence-transformers>=2.2.0
Requires-Dist: faiss-cpu>=1.7.4
Provides-Extra: langgraph
Requires-Dist: langgraph>=0.2.0; extra == "langgraph"
Provides-Extra: langchain
Requires-Dist: langchain>=0.1.0; extra == "langchain"
Requires-Dist: langchain-core>=0.1.0; extra == "langchain"
Provides-Extra: mcp
Requires-Dist: mcp>=1.0.0; extra == "mcp"
Provides-Extra: full
Requires-Dist: langgraph>=0.2.0; extra == "full"
Requires-Dist: langchain>=0.1.0; extra == "full"
Requires-Dist: langchain-core>=0.1.0; extra == "full"
Provides-Extra: full-mcp
Requires-Dist: langgraph>=0.2.0; extra == "full-mcp"
Requires-Dist: langchain>=0.1.0; extra == "full-mcp"
Requires-Dist: langchain-core>=0.1.0; extra == "full-mcp"
Requires-Dist: mcp>=1.0.0; extra == "full-mcp"
Provides-Extra: dev
Requires-Dist: pytest>=7.0.0; extra == "dev"
Requires-Dist: pytest-asyncio>=0.21.0; extra == "dev"
Requires-Dist: black>=23.0.0; extra == "dev"
Requires-Dist: mypy>=1.0.0; extra == "dev"
Dynamic: author
Dynamic: home-page
Dynamic: license-file
Dynamic: requires-python
